gajou_db/__init__.py
gajou_db/db_helper.py
gajou_db/singleton.py
gajou_db-0.1.3.dist-info/LICENSE
gajou_db-0.1.3.dist-info/METADATA
gajou_db-0.1.3.dist-info/WHEEL
gajou_db-0.1.3.dist-info/top_level.txt
gajou_db-0.1.3.dist-info/RECORD
