Metadata-Version: 2.1
Name: gajou-db
Version: 0.1.3
Summary: Base classes and helpers to make QA autotests with DB interaction
Home-page: https://github.com/ArtyomKomarenko/gajou-db
Author: Artyom Komarenko
Author-email: artyom.komarenko@mail.ru
License: MIT License
Classifier: Programming Language :: Python :: 3
Classifier: License :: OSI Approved :: MIT License
Classifier: Operating System :: OS Independent
Requires-Python: >=3.7
License-File: LICENSE
Requires-Dist: psycopg2-binary
